{
    "networks": [],
    "images": [
        {
            "name": "Ubuntu Certified 14.04",
            "className": "ubuntu-logo",
            "datasetName": "lx-ubuntu-14.04",
            "packageName": "g3-standard-4-smartos",
            "description": {
                "text": "Container optimized Ubuntu 14.04 64-bit image. Built to run on containers with bare metal speed.",
                "memory": 4,
                "cpu": 1,
                "disk": 131,
                "price": 0.128
            },
            "order": 1
        },
        {
            "name": "CentOS 6.6",
            "className": "centos-logo",
            "datasetName": "lx-centos-6",
            "packageName": "g3-standard-4-smartos",
            "description": {
                "text": "Container optimized CentOS 6.6 64-bit image. Built to run on containers with bare metal speed.",
                "memory": 4,
                "cpu": 1,
                "disk": 131,
                "price": 0.128
            },
            "order": 2
        },
        {
            "name": "Debian 7",
            "className": "debian-logo",
            "datasetName": "lx-debian-7",
            "packageName": "g3-standard-4-smartos",
            "description": {
                "text": "Container optimized Debian 7 64-bit image. Built to run on containers with bare metal speed.",
                "memory": 4,
                "cpu": 1,
                "disk": 131,
                "price": 0.128
            },
            "order": 3
        },
        {
            "name": "Windows Server 2008r2",
            "className": "windows-logo",
            "datasetName": "ws2008ent-r2-sp1",
            "packageName": "g3-standard-4-smartos",
            "description": {
                "text": "Windows Server 2008r2 Enterprise 64-bit image.",
                "memory": 4,
                "cpu": 1,
                "disk": 131,
                "price": 0.188
            },
            "order": 4
        },
        {
            "name": "Node.js",
            "className": "node-logo",
            "datasetName": "nodejs",
            "packageName": "g3-standard-4-smartos",
            "description": {
                "text": "A SmartOS 64-bit image with Node.js 0.12.0, npm 2.5.1, Git 2.2.1",
                "memory": 4,
                "cpu": 1,
                "disk": 131,
                "price": 0.128
            },
            "order": 5
        },
        {
            "name": "MongoDB",
            "className": "mongodb-logo",
            "datasetName": "mongodb",
            "packageName": "g3-standard-4-smartos",
            "description": {
                "text": "A SmartOS 64-bit image that comes with MongoDB 2.6.7",
                "memory": 4,
                "cpu": 1,
                "disk": 131,
                "price": 0.128
            },
            "order": 6
        },
        {
            "name": "Nginx",
            "className": "nginx-logo",
            "datasetName": "nginx",
            "packageName": "g3-standard-4-smartos",
            "description": {
                "text": "A SmartOS 64-bit image optimized as a Nginx 1.7.4 server.",
                "memory": 4,
                "cpu": 1,
                "disk": 131,
                "price": 0.128
            },
            "order": 7
        }
    ]
}
